nautobot_plugin_nornir/__init__.py
nautobot_plugin_nornir/app-config-schema.json
nautobot_plugin_nornir/constants.py
nautobot_plugin_nornir/db_management.py
nautobot_plugin_nornir/error_codes.py
nautobot_plugin_nornir/logger.py
nautobot_plugin_nornir/plugins/__init__.py
nautobot_plugin_nornir/plugins/credentials/__init__.py
nautobot_plugin_nornir/plugins/credentials/env_vars.py
nautobot_plugin_nornir/plugins/credentials/nautobot_orm.py
nautobot_plugin_nornir/plugins/credentials/nautobot_secrets.py
nautobot_plugin_nornir/plugins/credentials/settings_vars.py
nautobot_plugin_nornir/plugins/inventory/__init__.py
nautobot_plugin_nornir/plugins/inventory/nautobot_orm.py
nautobot_plugin_nornir/static/nautobot_plugin_nornir/docs/404.html
nautobot_plugin_nornir/static/nautobot_plugin_nornir/docs/admin/compatibility_matrix.html
nautobot_plugin_nornir/static/nautobot_plugin_nornir/docs/admin/install.html
nautobot_plugin_nornir/static/nautobot_plugin_nornir/docs/admin/migrating_to_v2.html
nautobot_plugin_nornir/static/nautobot_plugin_nornir/docs/admin/release_notes/index.html
nautobot_plugin_nornir/static/nautobot_plugin_nornir/docs/admin/release_notes/version_0.9.html
nautobot_plugin_nornir/static/nautobot_plugin_nornir/docs/admin/release_notes/version_1.0.html
nautobot_plugin_nornir/static/nautobot_plugin_nornir/docs/admin/release_notes/version_2.0.html
nautobot_plugin_nornir/static/nautobot_plugin_nornir/docs/admin/release_notes/version_2.1.html
nautobot_plugin_nornir/static/nautobot_plugin_nornir/docs/admin/release_notes/version_2.2.html
nautobot_plugin_nornir/static/nautobot_plugin_nornir/docs/admin/release_notes/version_2.3.html
nautobot_plugin_nornir/static/nautobot_plugin_nornir/docs/admin/release_notes/version_3.0.html
nautobot_plugin_nornir/static/nautobot_plugin_nornir/docs/admin/troubleshooting/E2001.html
nautobot_plugin_nornir/static/nautobot_plugin_nornir/docs/admin/troubleshooting/E2002.html
nautobot_plugin_nornir-3.0.0.dist-info/LICENSE
nautobot_plugin_nornir-3.0.0.dist-info/METADATA
nautobot_plugin_nornir-3.0.0.dist-info/WHEEL
nautobot_plugin_nornir-3.0.0.dist-info/RECORD
