Metadata-Version: 2.3
Name: nautobot-plugin-nornir
Version: 3.0.0
Summary: Nautobot App that provides a shim layer to simplify using Nornir within other Nautobot Apps and Nautobot Jobs
License: Apache-2.0
Keywords: nautobot,nautobot-app,nautobot-plugin
Author: Network to Code, LLC
Author-email: info@networktocode.com
Requires-Python: >=3.10,<3.14
Classifier: Development Status :: 5 - Production/Stable
Classifier: Intended Audience :: Developers
Classifier: License :: OSI Approved :: Apache Software License
Classifier: Programming Language :: Python :: 3
Classifier: Programming Language :: Python :: 3.10
Classifier: Programming Language :: Python :: 3.11
Classifier: Programming Language :: Python :: 3.12
Classifier: Programming Language :: Python :: 3.13
Provides-Extra: all
Requires-Dist: nautobot (>=3.0.0,<4.0.0)
Requires-Dist: nornir-nautobot (>=4.0.0,<5.0.0)
Project-URL: Bug Tracker, https://github.com/nautobot/nautobot-plugin-nornir/issues
Project-URL: Changelog, https://docs.nautobot.com/projects/plugin-nornir/en/latest/admin/release_notes/
Project-URL: Documentation, https://docs.nautobot.com/projects/plugin-nornir/en/latest/
Project-URL: Homepage, https://github.com/nautobot/nautobot-app-nornir
Project-URL: Repository, https://github.com/nautobot/nautobot-app-nornir
